oml/__init__.py
oml/const.py
oml/configs/__init__.py
oml/configs/criterion/arcface.yaml
oml/configs/criterion/mlp_arcface.yaml
oml/configs/criterion/surrogate_precision.yaml
oml/configs/criterion/triplet.yaml
oml/configs/criterion/triplet_plain.yaml
oml/configs/criterion/triplet_with_miner.yaml
oml/configs/extractor/ecapa_tdnn.yaml
oml/configs/extractor/extractor_with_mlp.yaml
oml/configs/extractor/resnet.yaml
oml/configs/extractor/vit.yaml
oml/configs/extractor/vit_clip.yaml
oml/configs/extractor/vit_unicom.yaml
oml/configs/logger/clearml.yaml
oml/configs/logger/mlflow.yaml
oml/configs/logger/neptune.yaml
oml/configs/logger/tensorboard.yaml
oml/configs/logger/wandb.yaml
oml/configs/miner/all_triplets.yaml
oml/configs/miner/hard_cluster.yaml
oml/configs/miner/hard_triplets.yaml
oml/configs/miner/miner_with_bank.yaml
oml/configs/miner/n_hard_triplets.yaml
oml/configs/miner/triplets_with_memory.yaml
oml/configs/optimizer/adadelta.yaml
oml/configs/optimizer/adagrad.yaml
oml/configs/optimizer/adam.yaml
oml/configs/optimizer/adamax.yaml
oml/configs/optimizer/adamw.yaml
oml/configs/optimizer/asgd.yaml
oml/configs/optimizer/lbfgs.yaml
oml/configs/optimizer/rmsprop.yaml
oml/configs/optimizer/rprop.yaml
oml/configs/optimizer/sgd.yaml
oml/configs/pairwise_model/concat_siamese.yaml
oml/configs/pairwise_model/linear_siamese.yaml
oml/configs/pairwise_model/trivial_distance_siamese.yaml
oml/configs/postprocessor/adaptive_thresholding.yaml
oml/configs/postprocessor/constant_thresholding.yaml
oml/configs/postprocessor/pairwise_reranker.yaml
oml/configs/sampler/balance.yaml
oml/configs/sampler/category_balance.yaml
oml/configs/sampler/distinct_category_balance.yaml
oml/configs/scheduler/cosine_annealing.yaml
oml/configs/scheduler/cyclic.yaml
oml/configs/scheduler/exponential.yaml
oml/configs/scheduler/lambda.yaml
oml/configs/scheduler/multi_step.yaml
oml/configs/scheduler/multiplicative.yaml
oml/configs/scheduler/one_cycle.yaml
oml/configs/scheduler/reduce_on_plateau.yaml
open_metric_learning-4.0.0.dist-info/licenses/LICENSE
open_metric_learning-4.0.0.dist-info/METADATA
open_metric_learning-4.0.0.dist-info/WHEEL
open_metric_learning-4.0.0.dist-info/top_level.txt
open_metric_learning-4.0.0.dist-info/RECORD
