Metadata-Version: 2.4
Name: open-metric-learning
Version: 4.0.0
Summary: OML is a PyTorch-based framework to train and validate the models producing high-quality embeddings.
Home-page: https://github.com/OML-Team/open-metric-learning
Author: Shabanov Aleksei
Author-email: shabanoff.aleksei@gmail.com
License: Apache License 2.0
Project-URL: Homepage, https://github.com/OML-Team/open-metric-learning
Project-URL: Bug Tracker, https://github.com/OML-Team/open-metric-learning/issues
Keywords: data-science,computer-vision,deep-learning,pytorch,metric-learning,representation-learning,pytorch-lightning
Classifier: Environment :: Console
Classifier: Natural Language :: English
Classifier: Operating System :: OS Independent
Classifier: License :: OSI Approved :: Apache Software License
Classifier: Intended Audience :: Developers
Classifier: Intended Audience :: Science/Research
Classifier: Topic :: Scientific/Engineering :: Artificial Intelligence
Classifier: Topic :: Scientific/Engineering :: Image Recognition
Classifier: Programming Language :: Python
Classifier: Programming Language :: Python :: 3.10
Classifier: Programming Language :: Python :: 3.11
Classifier: Programming Language :: Python :: Implementation :: CPython
Requires-Python: >=3.8,<4.0
License-File: LICENSE
Requires-Dist: torch>=2.0
Requires-Dist: numpy<2.0,>=1.24.4
Requires-Dist: torchvision
Requires-Dist: albumentations>1.0
Requires-Dist: opencv-python-headless>=4.1.1
Requires-Dist: pillow>=8.2
Requires-Dist: pandas>=1.0
Requires-Dist: matplotlib>3.5.2
Requires-Dist: validators>=0.18.0
Requires-Dist: gdown>=4.0
Requires-Dist: tensorboard
Provides-Extra: nlp
Requires-Dist: transformers>=4.0; extra == "nlp"
Provides-Extra: audio
Requires-Dist: soundfile==0.12.1; extra == "audio"
Requires-Dist: torchaudio; extra == "audio"
Requires-Dist: ipython; extra == "audio"
Provides-Extra: test
Requires-Dist: pytest>=7.2; extra == "test"
Requires-Dist: pre-commit==3.5.0; extra == "test"
Requires-Dist: python-dotenv>=0.17.0; extra == "test"
Requires-Dist: pyright[nodejs]==1.1.397; extra == "test"
Provides-Extra: pipelines
Requires-Dist: pytorch-lightning<=2.1.2,>=2.0; extra == "pipelines"
Requires-Dist: hydra-core==1.3.0; extra == "pipelines"
Provides-Extra: all
Requires-Dist: transformers>=4.0; extra == "all"
Requires-Dist: soundfile==0.12.1; extra == "all"
Requires-Dist: torchaudio; extra == "all"
Requires-Dist: ipython; extra == "all"
Requires-Dist: neptune<1.10.1,>=1.0.0; extra == "all"
Requires-Dist: wandb>=0.15.4; extra == "all"
Requires-Dist: mlflow>=2.0.0; extra == "all"
Requires-Dist: clearml>=1.5.0; extra == "all"
Requires-Dist: grad-cam==1.4.6; extra == "all"
Requires-Dist: pytorch-lightning<=2.1.2,>=2.0; extra == "all"
Requires-Dist: hydra-core==1.3.0; extra == "all"
Dynamic: author
Dynamic: author-email
Dynamic: classifier
Dynamic: description
Dynamic: description-content-type
Dynamic: home-page
Dynamic: keywords
Dynamic: license
Dynamic: license-file
Dynamic: project-url
Dynamic: provides-extra
Dynamic: requires-dist
Dynamic: requires-python
Dynamic: summary
